{
  "docusaurus-plugin-content-docs": {
    "default": {
      "path": "/docs",
      "versions": [
        {
          "name": "current",
          "label": "Next",
          "isLast": true,
          "path": "/docs",
          "mainDocId": "intro",
          "docs": [
            {
              "id": "architecture/djinn-board/architecture/agent",
              "path": "/docs/architecture/djinn-board/architecture/agent",
              "sidebar": "tutorialSidebar"
            },
            {
              "id": "architecture/djinn-board/architecture/authentication-server",
              "path": "/docs/architecture/djinn-board/architecture/authentication-server",
              "sidebar": "tutorialSidebar"
            },
            {
              "id": "architecture/djinn-board/architecture/event-bus",
              "path": "/docs/architecture/djinn-board/architecture/event-bus",
              "sidebar": "tutorialSidebar"
            },
            {
              "id": "architecture/djinn-board/architecture/gateway",
              "path": "/docs/architecture/djinn-board/architecture/gateway",
              "sidebar": "tutorialSidebar"
            },
            {
              "id": "architecture/djinn-board/architecture/persistance-layer",
              "path": "/docs/architecture/djinn-board/architecture/persistance-layer",
              "sidebar": "tutorialSidebar"
            },
            {
              "id": "architecture/djinn-board/architecture/platform",
              "path": "/docs/architecture/djinn-board/architecture/platform",
              "sidebar": "tutorialSidebar"
            },
            {
              "id": "architecture/djinn-board/architecture/web-client",
              "path": "/docs/architecture/djinn-board/architecture/web-client",
              "sidebar": "tutorialSidebar"
            },
            {
              "id": "architecture/djinn-board/installation",
              "path": "/docs/architecture/djinn-board/installation",
              "sidebar": "tutorialSidebar"
            },
            {
              "id": "architecture/djinn-board/overview",
              "path": "/docs/architecture/djinn-board/overview",
              "sidebar": "tutorialSidebar"
            },
            {
              "id": "architecture/djinn-board/security-model",
              "path": "/docs/architecture/djinn-board/security-model",
              "sidebar": "tutorialSidebar"
            },
            {
              "id": "architecture/djinn-client/gateway",
              "path": "/docs/architecture/djinn-client/gateway",
              "sidebar": "tutorialSidebar"
            },
            {
              "id": "architecture/djinn-client/overview",
              "path": "/docs/architecture/djinn-client/overview",
              "sidebar": "tutorialSidebar"
            },
            {
              "id": "architecture/djinn-client/web",
              "path": "/docs/architecture/djinn-client/web",
              "sidebar": "tutorialSidebar"
            },
            {
              "id": "architecture/djinn-cloud/community-edition",
              "path": "/docs/architecture/djinn-cloud/community-edition",
              "sidebar": "tutorialSidebar"
            },
            {
              "id": "architecture/djinn-cloud/enterprise-edition",
              "path": "/docs/architecture/djinn-cloud/enterprise-edition",
              "sidebar": "tutorialSidebar"
            },
            {
              "id": "architecture/djinn-cloud/overview",
              "path": "/docs/architecture/djinn-cloud/overview",
              "sidebar": "tutorialSidebar"
            },
            {
              "id": "architecture/overview",
              "path": "/docs/architecture/overview",
              "sidebar": "tutorialSidebar"
            },
            {
              "id": "c4",
              "path": "/docs/c4",
              "sidebar": "tutorialSidebar"
            },
            {
              "id": "intro",
              "path": "/docs/intro",
              "sidebar": "tutorialSidebar"
            },
            {
              "id": "reference-frameworks",
              "path": "/docs/reference-frameworks",
              "sidebar": "tutorialSidebar"
            },
            {
              "id": "use-case",
              "path": "/docs/use-case",
              "sidebar": "tutorialSidebar"
            }
          ],
          "sidebars": {
            "tutorialSidebar": {
              "link": {
                "path": "/docs/intro",
                "label": "intro"
              }
            }
          }
        }
      ],
      "breadcrumbs": true
    }
  }
}