{
  "docusaurus-plugin-content-docs": {
    "default": {
      "path": "/docs",
      "versions": [
        {
          "name": "current",
          "label": "Next",
          "isLast": true,
          "path": "/docs",
          "mainDocId": "intro",
          "docs": [
            {
              "id": "djinn-board/agent",
              "path": "/docs/djinn-board/agent",
              "sidebar": "tutorialSidebar"
            },
            {
              "id": "djinn-board/authentication-server",
              "path": "/docs/djinn-board/authentication-server",
              "sidebar": "tutorialSidebar"
            },
            {
              "id": "djinn-board/event-bus",
              "path": "/docs/djinn-board/event-bus",
              "sidebar": "tutorialSidebar"
            },
            {
              "id": "djinn-board/gateway",
              "path": "/docs/djinn-board/gateway",
              "sidebar": "tutorialSidebar"
            },
            {
              "id": "djinn-board/overview",
              "path": "/docs/djinn-board/overview",
              "sidebar": "tutorialSidebar"
            },
            {
              "id": "djinn-board/persistance-layer",
              "path": "/docs/djinn-board/persistance-layer",
              "sidebar": "tutorialSidebar"
            },
            {
              "id": "djinn-board/platform",
              "path": "/docs/djinn-board/platform",
              "sidebar": "tutorialSidebar"
            },
            {
              "id": "djinn-board/web-client",
              "path": "/docs/djinn-board/web-client",
              "sidebar": "tutorialSidebar"
            },
            {
              "id": "djinn-client/gateway",
              "path": "/docs/djinn-client/gateway",
              "sidebar": "tutorialSidebar"
            },
            {
              "id": "djinn-client/overview",
              "path": "/docs/djinn-client/overview",
              "sidebar": "tutorialSidebar"
            },
            {
              "id": "djinn-client/web",
              "path": "/docs/djinn-client/web",
              "sidebar": "tutorialSidebar"
            },
            {
              "id": "djinn-cloud/community-edition",
              "path": "/docs/djinn-cloud/community-edition",
              "sidebar": "tutorialSidebar"
            },
            {
              "id": "djinn-cloud/enterprise-edition",
              "path": "/docs/djinn-cloud/enterprise-edition",
              "sidebar": "tutorialSidebar"
            },
            {
              "id": "djinn-cloud/overview",
              "path": "/docs/djinn-cloud/overview",
              "sidebar": "tutorialSidebar"
            },
            {
              "id": "intro",
              "path": "/docs/intro",
              "sidebar": "tutorialSidebar"
            }
          ],
          "sidebars": {
            "tutorialSidebar": {
              "link": {
                "path": "/docs/intro",
                "label": "intro"
              }
            }
          }
        }
      ],
      "breadcrumbs": true
    }
  }
}